README.rst
setup.py
pyqqwry/__init__.py
pyqqwry/macro.py
pyqqwry/qqwry.py
pyqqwry/utils.py
pyqqwry.egg-info/PKG-INFO
pyqqwry.egg-info/SOURCES.txt
pyqqwry.egg-info/dependency_links.txt
pyqqwry.egg-info/not-zip-safe
pyqqwry.egg-info/requires.txt
pyqqwry.egg-info/top_level.txt